split_folder/__init__.py
split_folder/cli.py
split_folder/main.py
split_folder/requirements.txt
split_folder/split.py
split_folder-0.1.1.dist-info/WHEEL
split_folder-0.1.1.dist-info/METADATA
split_folder-0.1.1.dist-info/RECORD
