Metadata-Version: 2.1
Name: split-folder
Version: 0.1.1
Summary: Spilt folder into train/val/test subset
Author: Nivratti
Author-email: boyanenivratti@gmail.com
Requires-Python: >=3.8,<4.0
Classifier: Programming Language :: Python :: 3
Classifier: Programming Language :: Python :: 3.8
Classifier: Programming Language :: Python :: 3.9
Requires-Dist: nb-utils (>=0.1.0,<0.2.0)
